DarendeXingaiXiangtan/README.md
DarendeXingaiXiangtan/__init__.py
DarendeXingaiXiangtan/__main__.py
DarendeXingaiXiangtan/file.epub
DarendeXingaiXiangtan/index.html
DarendeXingaiXiangtan/css/__init__.py
DarendeXingaiXiangtan/css/annotations.css
DarendeXingaiXiangtan/css/main.css
DarendeXingaiXiangtan/css/normalize.css
DarendeXingaiXiangtan/css/popup.css
DarendeXingaiXiangtan/font/__init__.py
DarendeXingaiXiangtan/font/fontello.eot
DarendeXingaiXiangtan/font/fontello.svg
DarendeXingaiXiangtan/font/fontello.ttf
DarendeXingaiXiangtan/font/fontello.woff
DarendeXingaiXiangtan/img/__init__.py
DarendeXingaiXiangtan/img/annotator-glyph-sprite.png
DarendeXingaiXiangtan/img/annotator-icon-sprite.png
DarendeXingaiXiangtan/img/apple-touch-icon.png
DarendeXingaiXiangtan/img/cancelfullscreen.png
DarendeXingaiXiangtan/img/close.png
DarendeXingaiXiangtan/img/fullscreen.png
DarendeXingaiXiangtan/img/loader.gif
DarendeXingaiXiangtan/img/menu-icon.png
DarendeXingaiXiangtan/img/save.png
DarendeXingaiXiangtan/img/saved.png
DarendeXingaiXiangtan/img/settings-s.png
DarendeXingaiXiangtan/img/settings.png
DarendeXingaiXiangtan/img/star.png
DarendeXingaiXiangtan/js/__init__.py
DarendeXingaiXiangtan/js/epub.js
DarendeXingaiXiangtan/js/epub.min.js
DarendeXingaiXiangtan/js/epub.min.map
DarendeXingaiXiangtan/js/hooks.min.js
DarendeXingaiXiangtan/js/hooks.min.map
DarendeXingaiXiangtan/js/reader.js
DarendeXingaiXiangtan/js/reader.js.map
DarendeXingaiXiangtan/js/reader.min.js
DarendeXingaiXiangtan/js/reader.min.map
DarendeXingaiXiangtan/js/hooks/__init__.py
DarendeXingaiXiangtan/js/hooks/extensions/__init__.py
DarendeXingaiXiangtan/js/hooks/extensions/highlight.js
DarendeXingaiXiangtan/js/libs/__init__.py
DarendeXingaiXiangtan/js/libs/jquery.min.js
DarendeXingaiXiangtan/js/libs/localforage.min.js
DarendeXingaiXiangtan/js/libs/screenfull.js
DarendeXingaiXiangtan/js/libs/screenfull.min.js
DarendeXingaiXiangtan/js/libs/zip.min.js
DarendeXingaiXiangtan/js/plugins/__init__.py
darende_xingai_xiangtan-2022.10.11.0.dist-info/METADATA
darende_xingai_xiangtan-2022.10.11.0.dist-info/WHEEL
darende_xingai_xiangtan-2022.10.11.0.dist-info/entry_points.txt
darende_xingai_xiangtan-2022.10.11.0.dist-info/top_level.txt
darende_xingai_xiangtan-2022.10.11.0.dist-info/RECORD
